pydesigner/__init__.py
pydesigner/__main__.py
pydesigner-0.0.0.dist-info/LICENSE
pydesigner-0.0.0.dist-info/METADATA
pydesigner-0.0.0.dist-info/WHEEL
pydesigner-0.0.0.dist-info/top_level.txt
pydesigner-0.0.0.dist-info/RECORD
